jira_timesheet_cli/__init__.py
jira_timesheet_cli/arguments.py
jira_timesheet_cli/base.yaml
jira_timesheet_cli/book-time.yaml
jira_timesheet_cli/book_time.py
jira_timesheet_cli/register-completion.txt
jira_timesheet_cli-1.0.0.dist-info/entry_points.txt
jira_timesheet_cli-1.0.0.dist-info/LICENSE
jira_timesheet_cli-1.0.0.dist-info/WHEEL
jira_timesheet_cli-1.0.0.dist-info/METADATA
jira_timesheet_cli-1.0.0.dist-info/RECORD
